layout3mesh/__init__.py
layout3mesh/cli.py
layout3mesh/data.py
layout3mesh/layout3mesh.py
layout3mesh-0.1.2.dist-info/entry_points.txt
layout3mesh-0.1.2.dist-info/LICENSE
layout3mesh-0.1.2.dist-info/WHEEL
layout3mesh-0.1.2.dist-info/METADATA
layout3mesh-0.1.2.dist-info/RECORD
