Metadata-Version: 2.1
Name: layout3mesh
Version: 0.1.2
Summary: A tool to generate 3D meshes from 2D integrated circuit layouts
Home-page: https://github.com/das-dias/layout3mesh
License: GPLv2
Keywords: layout,3D-mesh,gds2,oasis
Author: dasdias
Author-email: das.dias6@gmail.com
Requires-Python: >=3.9,<3.13
Classifier: License :: Other/Proprietary License
Classifier: Programming Language :: Python :: 3
Classifier: Programming Language :: Python :: 3.10
Classifier: Programming Language :: Python :: 3.9
Requires-Dist: PyYAML (>=6.0.1,<7.0.0)
Requires-Dist: docopt (>=0.6.2,<0.7.0)
Requires-Dist: gdstk (>=0.9.42,<0.10.0)
Requires-Dist: loguru (>=0.7.0,<0.8.0)
Requires-Dist: mapbox-earcut (>=1.0.1,<2.0.0)
Requires-Dist: scipy (>=1.11.1,<2.0.0)
Requires-Dist: shapely (>=2.0.1,<3.0.0)
Requires-Dist: trimesh (>=3.23.1,<4.0.0)
Project-URL: Repository, https://github.com/das-dias/layout3mesh
